nonebot_plugin_fire/__init__.py
nonebot_plugin_fire-1.0.3.dist-info/LICENSE
nonebot_plugin_fire-1.0.3.dist-info/METADATA
nonebot_plugin_fire-1.0.3.dist-info/WHEEL
nonebot_plugin_fire-1.0.3.dist-info/top_level.txt
nonebot_plugin_fire-1.0.3.dist-info/RECORD
