Metadata-Version: 2.1
Name: nonebot-plugin-fire
Version: 1.0.3
Summary: nonebot2 plugin fire
Home-page: https://github.com/25252www/nonebot_plugin_fire
Author: moyusoldier
Author-email: 1433221642@qq.com
License: UNKNOWN
Keywords: pip,nonebot2,nonebot,fire,nonebot_plugin
Platform: any
Classifier: Programming Language :: Python :: 3
Classifier: License :: OSI Approved :: MIT License
Classifier: Operating System :: OS Independent
License-File: LICENSE
Requires-Dist: nonebot-plugin-apscheduler (>=0.1.2)
Requires-Dist: nonebot2 (>=2.0.0-beta.2)
Requires-Dist: nonebot-adapter-onebot (>=2.0.0b1)
